neuralstyletransfer/__init__.py
neuralstyletransfer/about.py
neuralstyletransfer/model.py
neuralstyletransfer/style_transfer.py
neural_style_transfer-1.0.6.dist-info/LICENSE
neural_style_transfer-1.0.6.dist-info/METADATA
neural_style_transfer-1.0.6.dist-info/WHEEL
neural_style_transfer-1.0.6.dist-info/top_level.txt
neural_style_transfer-1.0.6.dist-info/RECORD
