Metadata-Version: 2.1
Name: neural-style-transfer
Version: 1.0.6
Summary: This is the python library to convert style of content image to given style image
Home-page: UNKNOWN
Author: Divy Shah
Author-email: divyshah1712@gmail.com
License: Apache License 2.0
Platform: UNKNOWN
License-File: LICENSE
Requires-Dist: pandas (>=1.1.5)
Requires-Dist: numpy (>=1.9.1)
Requires-Dist: tensorflow (==2.6.0)
Requires-Dist: keras (==2.6.0)
Requires-Dist: opencv-python (==4.5.3.56)
Requires-Dist: Pillow (==8.2.0)
Requires-Dist: requests (>=2.23.0)
